{
    "data": [
        {
                "_id": "64978146ce56f1a336e9bfe2",
                "name": "Mexico City",
                "banner": "https://firebasestorage.googleapis.com/v0/b/mytinerary-6ce01.appspot.com/o/MEXICO%2Fgaleria%2Fd7343474-f49d-4e75-86e8-fe5037998b3a.jpg?alt=media&token=49af936b-07e6-40f5-8e02-60db3ff95a30",
                "country": "United States of Mexico",
                "image": "https://firebasestorage.googleapis.com/v0/b/mytinerary-6ce01.appspot.com/o/MEXICO%2FciudadDeMexicojpg.jpg?alt=media&token=05723253-a71b-43e2-b7a8-723fe717fd40",
                "info": "Come and discover the metropolis of Mexico City, where contemporary life mixes with ancient history that goes back to the Aztecs. Vibrant dining options, nightlife, arts and culture",
                "phrase": "Gateway of Mexico",
                "region": "Latin America",
                "galDos": "https://firebasestorage.googleapis.com/v0/b/mytinerary-6ce01.appspot.com/o/MEXICO%2Fgaleria%2FgalDos.jpg?alt=media&token=18f14567-595a-40c4-9ffd-484dd68e7ad8",
                "galTres": "https://firebasestorage.googleapis.com/v0/b/mytinerary-6ce01.appspot.com/o/MEXICO%2Fgaleria%2FgalTres.jpg?alt=media&token=366cae29-0cb4-4fe6-a3d0-ee52dbdb6425",
                "galUno": "https://firebasestorage.googleapis.com/v0/b/mytinerary-6ce01.appspot.com/o/MEXICO%2Fgaleria%2FgalUno.jpg?alt=media&token=86145daf-9d6a-49be-a8c1-ae754d9ab8a1",
                "language": "Spanish"
        },
        {
            "_id": "6498d990931a59b9c4c80ab6",
            "name": "Buenos Aires",
            "banner": "https://firebasestorage.googleapis.com/v0/b/mytinerary-6ce01.appspot.com/o/BUENOS%20AIRES%2Fgalery%2F11b824ed-30be-4446-8ad7-cf7d68dee925.jpg?alt=media&token=aa24fb96-2f88-41ef-bc91-ef3d3ba638a9",
            "country": "Argentinian Republic",
            "language": "Spanish",
            "image": "https://firebasestorage.googleapis.com/v0/b/mytinerary-6ce01.appspot.com/o/BUENOS%20AIRES%2FbuenosAires.jpg?alt=media&token=782ef8de-7d1c-45f8-b432-145098ad0777",
            "info": "Meet the Queen of the Rio de la Plata. The great cosmopolitan capital of Argentina, a captivating, seductive city full of vibrant energy.\n\nLet yourself be dazzled by its architecture, where the European heritage stands out. Their dances and their urban life that continues until dawn.",
            "phrase": "Gateway of Argentina",
            "region": "Latin America",
            "galUno": "https://firebasestorage.googleapis.com/v0/b/mytinerary-6ce01.appspot.com/o/BUENOS%20AIRES%2Fgalery%2FgalTres.jpg?alt=media&token=7200101b-a3ed-42cb-a003-32d2dab44fd8",
            "galDos": "https://firebasestorage.googleapis.com/v0/b/mytinerary-6ce01.appspot.com/o/BUENOS%20AIRES%2Fgalery%2FgalDos.jpg?alt=media&token=160fb7fb-0ebe-4c03-b92c-c680279c2785",
            "galTres": "https://firebasestorage.googleapis.com/v0/b/mytinerary-6ce01.appspot.com/o/BUENOS%20AIRES%2Fgalery%2FgalUno.jpg?alt=media&token=c51c22ce-cd09-4fb5-8c3d-e044167c3b91"
        },
        {
            "_id": "6498de3c931a59b9c4c80ab7",
            "name": "The Asuncion",
            "banner": "https://firebasestorage.googleapis.com/v0/b/mytinerary-6ce01.appspot.com/o/MARGARITA%2Fgalery%2F978f94e5-58e4-48ce-8636-b525745434fe.jpg?alt=media&token=4a3431aa-fe3b-4014-ae19-a46f10b49cfe",
            "country": "Bolivarian Republic of Venezuela",
            "language": "Spanish",
            "image": "https://firebasestorage.googleapis.com/v0/b/mytinerary-6ce01.appspot.com/o/MARGARITA%2FMargaritas.jpg?alt=media&token=0f98628b-228d-4ac1-a750-d3325c36724b",
            "info": "Visit Asuncion and tour this beautiful and quiet city through its pedestrian streets.\n\nTour the Isla de Margarita and enjoy beautiful beaches and the warm waters of the Caribbean Sea. Be sure to take a walk through some of its towns, which have many interesting treasures waiting for you to discover them.\n\nLet yourself be dazzled by its architecture, where the European heritage stands out. Their dances and their urban life that continues until dawn.",
            "phrase": "The pearl of the caribbean in Venezuela",
            "region": "Latin America",
            "galUno": "https://firebasestorage.googleapis.com/v0/b/mytinerary-6ce01.appspot.com/o/MARGARITA%2Fgalery%2FgalUno.jpg?alt=media&token=7d0a8a82-e484-44a9-b52b-6e8fa7c8ffab",
            "galDos": "https://firebasestorage.googleapis.com/v0/b/mytinerary-6ce01.appspot.com/o/MARGARITA%2Fgalery%2FgalDos.jpg?alt=media&token=57309fde-c779-47e6-a368-aaabed269b3b",
            "galTres": "https://firebasestorage.googleapis.com/v0/b/mytinerary-6ce01.appspot.com/o/MARGARITA%2Fgalery%2FgalTres.jpg?alt=media&token=3c5c3a22-ec6d-4162-bc38-5e290091bd7f"
        },
        {
            "_id": "6498e0f4931a59b9c4c80ab8",
            "name": "Hong Kong",
            "banner": "https://firebasestorage.googleapis.com/v0/b/mytinerary-6ce01.appspot.com/o/HONG%20KONG%2Fgalery%2Fc3f863b0-410d-4fde-aca0-4c579147b78b.jpg?alt=media&token=86faaabd-34ce-4e77-8b52-961a2c3fc670",
            "country": "Popular Republic of China",
            "language": "Chinese",
            "image": "https://firebasestorage.googleapis.com/v0/b/mytinerary-6ce01.appspot.com/o/HONG%20KONG%2FHongKong.jpg?alt=media&token=903ae7b5-416a-47e4-94ea-0770f491faa2",
            "info": "Explore this important port city and be dazzled by its landscape full of skyscrapers. Get to know the traditional Chinese architecture and then be sure to visit the famous Temple Street Night Market with an incomparable gastronomic scene",
            "phrase": "The island of perfumed waters in China",
            "region": "Asia",
            "galUno": "https://firebasestorage.googleapis.com/v0/b/mytinerary-6ce01.appspot.com/o/HONG%20KONG%2Fgalery%2FgalUno.jpeg?alt=media&token=4eb149ff-0b2d-460e-8d52-0ea9b1283b4e",
            "galDos": "https://firebasestorage.googleapis.com/v0/b/mytinerary-6ce01.appspot.com/o/HONG%20KONG%2Fgalery%2FgalDos.jpg?alt=media&token=f1d464b3-b2d6-407e-9f4f-c7cd9d31ce2a",
            "galTres": "https://firebasestorage.googleapis.com/v0/b/mytinerary-6ce01.appspot.com/o/HONG%20KONG%2Fgalery%2FgalTres.jpg?alt=media&token=5a3bca43-565a-43d1-96aa-04bc78196f9e"
        },
        {
            "_id": "6498e2ab931a59b9c4c80ab9",
            "name": "Ibiza",
            "banner": "https://firebasestorage.googleapis.com/v0/b/mytinerary-6ce01.appspot.com/o/IBIZA%2Fgalery%2F03cb074a-be93-4eab-92dc-8de3209d4eef.jpg?alt=media&token=df571671-997f-4659-8139-bed7e5a66174",
            "country": "Spain",
            "language":"Spanish",
            "image": "https://firebasestorage.googleapis.com/v0/b/mytinerary-6ce01.appspot.com/o/IBIZA%2Fibiza.jpg?alt=media&token=6ee380b5-000b-4b5a-a049-1121b9f5950d",
            "info": "Come and enjoy its more than 50 beaches and many restaurants, bars and water sports; and nightclubs, of course. Enjoy the European destination with the greatest nightlife attraction: party until you can't anymore",
            "phrase": "Get to know the Balearic Islands: Spain",
            "region": "Europe",
            "galUno":"https://firebasestorage.googleapis.com/v0/b/mytinerary-6ce01.appspot.com/o/IBIZA%2Fgalery%2Fgaldos.jpg?alt=media&token=abebbc41-b518-4f4f-a059-3e1878bd7d17",
            "galDos":"https://firebasestorage.googleapis.com/v0/b/mytinerary-6ce01.appspot.com/o/IBIZA%2Fgalery%2FgalUno.jpg?alt=media&token=8dfbacfd-5adb-456f-80f9-04e019021a4f",
            "galTres":"https://firebasestorage.googleapis.com/v0/b/mytinerary-6ce01.appspot.com/o/IBIZA%2Fgalery%2FgalTres.jpeg?alt=media&token=4bd02d58-fd4f-4f49-9ff1-5fb29e132add"
        },
        {
            "_id": "6498e442931a59b9c4c80aba",
            "name": "Agra",
            "banner": "https://firebasestorage.googleapis.com/v0/b/mytinerary-6ce01.appspot.com/o/INDIA%2Fgalery%2F2cb87f7f-af91-4ff2-8387-8955eb519dc3.jpg?alt=media&token=45b497f9-3aa9-4226-96c0-42367f93b277",
            "country": "Republic of India",
            "language":"Hindi",
            "image": "https://firebasestorage.googleapis.com/v0/b/mytinerary-6ce01.appspot.com/o/INDIA%2Ftaj-mahal.jpg?alt=media&token=391ddf49-ad31-4b30-bd84-3a59bb1de703",
            "info": "Come to know this historic city and visit the most famous mausoleum in the world: The Taj Mahal",
            "phrase": "Get to know Agra: India",
            "region": "Asia",
            "galUno":"https://firebasestorage.googleapis.com/v0/b/mytinerary-6ce01.appspot.com/o/INDIA%2Fgalery%2FgalDos.jpg?alt=media&token=c9ce151d-47bb-4dbd-b4e2-a6aacbc8c9d5",
            "galDos":"https://firebasestorage.googleapis.com/v0/b/mytinerary-6ce01.appspot.com/o/INDIA%2Fgalery%2FgalTres.jpg?alt=media&token=7d60e645-b6d0-46eb-9cbf-135bcbfb0f90",
            "galTres":"https://firebasestorage.googleapis.com/v0/b/mytinerary-6ce01.appspot.com/o/INDIA%2Fgalery%2FgalUno.jpg?alt=media&token=82aacfb6-816f-4994-a1d8-fcc6361d5734"
        },
        {
            "_id":"649a0c66bcdfa1ab076e17b7",
            "name": "Madrid",
            "banner": "https://firebasestorage.googleapis.com/v0/b/mytinerary-6ce01.appspot.com/o/MADRID%2Fgalery%2F0969b4eb-43de-4573-9002-ddb635be0653.jpg?alt=media&token=a01960e8-4b30-4e86-8e7d-1d4c2b7cac69",
            "country": "Spain",
            "language": "Spanish",
            "image": "https://firebasestorage.googleapis.com/v0/b/mytinerary-6ce01.appspot.com/o/MADRID%2Fmadrid.jpg?alt=media&token=47758440-8656-4b39-a970-1cf2a3390e9b",
            "info": "Come and discover one of the most populated cities in Europe. Madrid is an influential cultural center, where you can enjoy impressive architectural tours and museum visits. Do not forget that your tour will be better tasting Spanish food and wines.",
            "phrase": "The fairy tale capital of Spain",
            "region": "Europe",
            "galUno":"https://firebasestorage.googleapis.com/v0/b/mytinerary-6ce01.appspot.com/o/MADRID%2Fgalery%2FgalUno.jpg?alt=media&token=c89a1404-13e0-4f78-be3e-668f202d5350",
            "galDos":"https://firebasestorage.googleapis.com/v0/b/mytinerary-6ce01.appspot.com/o/MADRID%2Fgalery%2FgalDos.jpg?alt=media&token=e8244d02-6925-441f-9d83-29ebfe434f23",
            "galTres":"https://firebasestorage.googleapis.com/v0/b/mytinerary-6ce01.appspot.com/o/MADRID%2Fgalery%2Fgaltres.jpg?alt=media&token=f2723a96-4110-4f74-8436-e04ec058020d"
        },
        {
            "_id": "649a0cedbcdfa1ab076e17b8",
            "name": "Male",
            "banner": "https://firebasestorage.googleapis.com/v0/b/mytinerary-6ce01.appspot.com/o/MALDIVES%2Fgalery%2F76d98562-14ce-412b-9fa3-e786b59e70a8.jpg?alt=media&token=e44dd6ea-f9e3-4482-b63a-619a9dc5ee50",
            "country": "Republic of the Maldives",
            "language":"Dhivehi",
            "image": "https://firebasestorage.googleapis.com/v0/b/mytinerary-6ce01.appspot.com/o/MALDIVES%2FMaldives.jpg?alt=media&token=33674e33-ffa3-4bb1-a855-96604d721178",
            "info": "Come and enjoy the sun and the paradisiacal view on the beaches of Malé. Sign up for underwater photo sessions and be sure to try its culinary delights in the local markets where you will find fresh products",
            "phrase": "Male, the Soul of the Maldives",
            "region": "Asia",
            "galUno":"https://firebasestorage.googleapis.com/v0/b/mytinerary-6ce01.appspot.com/o/MALDIVES%2Fgalery%2FgalUno.jpg?alt=media&token=ac770f0b-9164-409e-9e69-401fe01634c2",
            "galDos":"https://firebasestorage.googleapis.com/v0/b/mytinerary-6ce01.appspot.com/o/MALDIVES%2Fgalery%2FgalDps.jpg?alt=media&token=3150fe3c-a937-4f48-b037-680dcba507d7",
            "galTres":"https://firebasestorage.googleapis.com/v0/b/mytinerary-6ce01.appspot.com/o/MALDIVES%2Fgalery%2FgalTres.jpg?alt=media&token=90ca8ebe-ada8-458f-80af-c785f6877d83"
        },
        {
            "_id": "649a110cbcdfa1ab076e17b9",
            "name": "Munich",
            "banner": "https://firebasestorage.googleapis.com/v0/b/mytinerary-6ce01.appspot.com/o/MUNICH%2Fgalery%2F3169f8f2-9011-4543-8741-6cd9e2ca0118.jpg?alt=media&token=55e755a4-fffd-4ee0-aaa5-01ed2bde9be6",
            "country": "Federal Republic of Germany",
            "language":"German",
            "image": "https://firebasestorage.googleapis.com/v0/b/mytinerary-6ce01.appspot.com/o/MUNICH%2Fmunich.jpg?alt=media&token=cf1cdede-2d14-41c3-b867-99961d4b52e3",
            "info": "Explore Munich and let yourself be carried away by its Bavarian charm. Explore its monuments and museums with high historical value. If you enjoy a beer, you can't miss visiting Hofbräuhaus",
            "phrase": "Munich likes you: Germany",
            "region": "Europe",
            "galUno":"https://firebasestorage.googleapis.com/v0/b/mytinerary-6ce01.appspot.com/o/MUNICH%2Fgalery%2FgalTres.png?alt=media&token=7464c297-f141-4372-a4c3-2cb651466917",
            "galDos":"https://firebasestorage.googleapis.com/v0/b/mytinerary-6ce01.appspot.com/o/MUNICH%2Fgalery%2FgalDos.jpg?alt=media&token=899148e1-46ab-4305-8508-b2428f2aceb1",
            "galTres":"https://firebasestorage.googleapis.com/v0/b/mytinerary-6ce01.appspot.com/o/MUNICH%2Fgalery%2FgalUno.jpg?alt=media&token=2842351f-050b-4cee-9b76-b14f253370e2"
        },
        {
            "_id": "649a137ebcdfa1ab076e17ba",
            "name": "Paris",
            "banner": "https://firebasestorage.googleapis.com/v0/b/mytinerary-6ce01.appspot.com/o/PARIS%2Fgalery%2Fc0c54d51-8208-4a49-84bf-35c0c2ee7806.jpg?alt=media&token=eadf90ff-8c93-4dc4-80f2-7d6db2259b8b",
            "country": "French Republic",
            "language":"French",
            "image": "https://firebasestorage.googleapis.com/v0/b/mytinerary-6ce01.appspot.com/o/PARIS%2Fparis.jpg?alt=media&token=85839270-3709-45d4-862a-4f053ec08c9f",
            "info": "Get to know the most visited tourist destination in the world. Paris is one of the most important cities in the field of culture, gastronomy, fashion and luxury. Come and see its large stone and wrought iron buildings, its cozy cafes and the curves of the Seine bank are absolutely cinematic",
            "phrase": "City of Light in France",
            "region": "Europe",
            "galUno":"https://firebasestorage.googleapis.com/v0/b/mytinerary-6ce01.appspot.com/o/PARIS%2Fgalery%2FgalDps.jpg?alt=media&token=28ec6d24-cba9-4d8a-9662-1e6dba44ccb9",
            "galDos":"https://firebasestorage.googleapis.com/v0/b/mytinerary-6ce01.appspot.com/o/PARIS%2Fgalery%2FgalTres.jpeg?alt=media&token=d596c29f-1f89-43bf-8932-a44eff8d0710",
            "galTres":"https://firebasestorage.googleapis.com/v0/b/mytinerary-6ce01.appspot.com/o/PARIS%2Fgalery%2FgalUno.jpg?alt=media&token=3f776c3a-f860-4d8e-b34a-3c63c941d04a"
        },
        {
            "_id": "",
            "name": "Bangkok",
            "banner": "https://firebasestorage.googleapis.com/v0/b/mytinerary-6ce01.appspot.com/o/Bangkok%2Fgalery%2Fba5315ed-8cda-4473-83e8-379abb8fac15.jpg?alt=media&token=fe0713e7-211b-42e8-a720-6651c4391cbe",
            "country": "Thailand",
            "language":"Thai",
            "image": "https://firebasestorage.googleapis.com/v0/b/mytinerary-6ce01.appspot.com/o/Bangkok%2Fbankok.jpg?alt=media&token=df4eb9c0-5e51-4494-b5e2-eef75a64284b",
            "info": "Come to Bangkok practice some yoga, try Thai food, enjoy a massage and let yourself be carried away by the views of this City. Get to know its magnificent Buddhist temples and take a boat tour of its river and its canals. Don't miss out on visiting its grandiose Royal Palace",
            "phrase": "The city of Los Angeles",
            "region": "Asia",
            "galUno":"https://firebasestorage.googleapis.com/v0/b/mytinerary-6ce01.appspot.com/o/Bangkok%2Fgalery%2FgalUno.jpg?alt=media&token=5c41b2fa-2a26-4024-989b-e8d3009c5e63",
            "galDos":"https://firebasestorage.googleapis.com/v0/b/mytinerary-6ce01.appspot.com/o/Bangkok%2Fgalery%2FgalTres.jpg?alt=media&token=4b7f8f1a-94c6-4669-9788-08a963c35ad5",
            "galTres":"https://firebasestorage.googleapis.com/v0/b/mytinerary-6ce01.appspot.com/o/Bangkok%2Fgalery%2FgalDos.jpg?alt=media&token=1dccd36d-5cfb-43f8-b2da-429a70c344b4"
        },
        {
            "_id": "",
            "name": "Bariloche",
            "banner": "https://firebasestorage.googleapis.com/v0/b/mytinerary-6ce01.appspot.com/o/BARILOCHE%2Fgalery%2Fbed55553-27f4-4e38-8ed3-97af915b6aa1.jpg?alt=media&token=51136b25-ab3c-4ac2-8b33-da8d242eead0",
            "country": "Argentinian Republic",
            "language":"Spanish",
            "image": "https://firebasestorage.googleapis.com/v0/b/mytinerary-6ce01.appspot.com/o/BARILOCHE%2Fbariloche.jpg?alt=media&token=e8e02e73-226f-486a-a5a6-251a18535fe5",
            "info": "Get to know the most important tourist center in Argentine Patagonia. Enjoy lakes, forests and mountains. Do outdoor activities: walks, horseback riding, trout fishing, skiing, excursions and boat or catamaran trips on Lake Nahuel Huapi",
            "phrase": "You are where you wanted to be. You are in Bariloche, Argentina",
            "region": "Latin America",
            "galUno":"https://firebasestorage.googleapis.com/v0/b/mytinerary-6ce01.appspot.com/o/BARILOCHE%2Fgalery%2Fgaluno.jpg?alt=media&token=feec22d5-4911-43b0-bb2a-81096accb0b9",
            "galDos":"https://firebasestorage.googleapis.com/v0/b/mytinerary-6ce01.appspot.com/o/BARILOCHE%2Fgalery%2Fgaldos.jpg?alt=media&token=33b38400-60c7-46f2-a91a-008f65c2aff7",
            "galTres":"https://firebasestorage.googleapis.com/v0/b/mytinerary-6ce01.appspot.com/o/BARILOCHE%2Fgalery%2Fgaltres.jpg?alt=media&token=fd1c8fdf-e864-4873-b9a7-9f59345500eb"
        },
        {
            "_id": "",
            "name": "Bogota",
            "banner": "https://firebasestorage.googleapis.com/v0/b/mytinerary-6ce01.appspot.com/o/BOGOTA%2Fgalery%2F0d7252cb-8b2e-4c1b-9c9c-c404fd4117b6.jpg?alt=media&token=9fddc959-a3c9-4d5a-a917-76ed732747ae",
            "country": "Republic of Colombia",
            "language":"Spanish",
            "image": "https://firebasestorage.googleapis.com/v0/b/mytinerary-6ce01.appspot.com/o/BOGOTA%2Fbogota.jpg?alt=media&token=93a55273-e7de-434c-9b40-99ddc4e383da",
            "info": "Fill yourself with the energy of this metropolitan center of Colombia, visit hundreds of eclectic and authentic places to eat, fantastic wines and frequent food festivals.",
            "phrase": "Get to know the South American Athens in Colombia",
            "region": "Latin America",
            "galUno":"https://firebasestorage.googleapis.com/v0/b/mytinerary-6ce01.appspot.com/o/BOGOTA%2Fgalery%2Fgaltres.jpg?alt=media&token=009c32c2-935f-40a6-9a9f-7efe837e398d",
            "galDos":"https://firebasestorage.googleapis.com/v0/b/mytinerary-6ce01.appspot.com/o/BOGOTA%2Fgalery%2Fgaldos.jpg?alt=media&token=8d383474-833a-4893-9bc9-215a4ae58116",
            "galTres":"https://firebasestorage.googleapis.com/v0/b/mytinerary-6ce01.appspot.com/o/BOGOTA%2Fgalery%2Fgal1.jpg?alt=media&token=f948133d-d870-416a-9ee2-76d3992073de"
        },
        {
            "_id": "",
            "name": "Bora Bora",
            "banner": "https://firebasestorage.googleapis.com/v0/b/mytinerary-6ce01.appspot.com/o/BORABORA%2Fgalery%2F48dc8c3a-6ac1-4ff4-a5c8-305fe2180e63.jpg?alt=media&token=d8dbfa27-32a9-4b92-8460-e3a4f78d6fac",
            "country": "French Republic",
            "language":"French",
            "image": "https://firebasestorage.googleapis.com/v0/b/mytinerary-6ce01.appspot.com/o/BORABORA%2Fbora.jpg?alt=media&token=78dbe65e-e687-4561-a6a0-bc8be92c0a4c",
            "info": "Turquoise lagoons, soft white sands and deep orange sunsets set the stage for romance on an island so nice it was named twice. Relax on the beautiful beaches, snorkel the tropical reefs or enjoy a refreshing cocktail at one of the many luxury hotels and resorts on the island.",
            "phrase": "Created by the gods",
            "region": "Oceania",
            "galUno":"https://firebasestorage.googleapis.com/v0/b/mytinerary-6ce01.appspot.com/o/BORABORA%2Fgalery%2FgalTres.jpg?alt=media&token=0db883e1-4603-44b0-90a9-ba6874054e36",
            "galDos":"https://firebasestorage.googleapis.com/v0/b/mytinerary-6ce01.appspot.com/o/BORABORA%2Fgalery%2FgalUno.jpg?alt=media&token=c17ac2d7-eaac-4311-9a6b-63b62c7aa6fc",
            "galTres":"https://firebasestorage.googleapis.com/v0/b/mytinerary-6ce01.appspot.com/o/BORABORA%2Fgalery%2FgalDos.jpg?alt=media&token=0d8846fe-d307-48b2-b0b0-211b79b444f7"
        },
        {
            "_id": "",
            "name": "Cancun",
            "banner": "https://firebasestorage.googleapis.com/v0/b/mytinerary-6ce01.appspot.com/o/CANCUN%2Fgalery%2Fd692a24b-85e6-4db7-89b5-e6cb31e2a2b4.jpg?alt=media&token=2fe7abaf-1481-4847-8bcd-e6ec16482b27",
            "country": "United States of Mexico",
            "language":"Spanish",
            "image": "https://firebasestorage.googleapis.com/v0/b/mytinerary-6ce01.appspot.com/o/CANCUN%2Fcancun.jpg?alt=media&token=781019d5-dcd1-4e59-b498-664cd7cbee8b",
            "info": "Come and discover the most recognized Mexican tourist center in the world, created especially for vacations. Its velvety beaches are some of the best the Caribbean has to offer, while divers and snorkelers will find plenty of action in the waves.",
            "phrase": "Where beauty and culture meet",
            "region": "Latin America",
            "galUno":"https://firebasestorage.googleapis.com/v0/b/mytinerary-6ce01.appspot.com/o/CANCUN%2Fgalery%2Fgal.jpg?alt=media&token=5ea06b54-e36b-4864-a75a-ffa9c5bfc563",
            "galDos":"https://firebasestorage.googleapis.com/v0/b/mytinerary-6ce01.appspot.com/o/CANCUN%2Fgalery%2FgalUno.jpg?alt=media&token=ba33f9d8-c59e-4cdb-ba50-acde0608100a",
            "galTres":"https://firebasestorage.googleapis.com/v0/b/mytinerary-6ce01.appspot.com/o/CANCUN%2Fgalery%2FgalTres.jpg?alt=media&token=21f07d2e-3177-4376-b028-234fbc8d9d69"
        },
        {
            "_id": "",
            "name": "Cusco",
            "banner": "https://firebasestorage.googleapis.com/v0/b/mytinerary-6ce01.appspot.com/o/CUSCO%2Fgalery%2F558e39c6-d8c6-4d4b-bec0-69cf807b02d6.jpg?alt=media&token=c7d27453-3ad8-4ea0-bae8-6ec6ec727432",
            "country": "Republic of Peru",
            "language":"Spanish",
            "image": "https://firebasestorage.googleapis.com/v0/b/mytinerary-6ce01.appspot.com/o/CUSCO%2FGI-930824730_MachuPicchu.jpg?alt=media&token=fb9b7b89-fd83-460f-9683-e7c94ea1b69b",
            "info": "Visit Cusco and you will be able to learn more about the mysterious culture of the Incas, and then start the trip to Machu Picchu. A whole adventure awaits you through different landscapes that enhance the trip, you will be able to appreciate all the urban distribution and the harmony that this enclosure has with nature.",
            "phrase": "Get to know the old mountain in the Andes Mountains",
            "region": "Latin America",
            "galUno":"https://firebasestorage.googleapis.com/v0/b/mytinerary-6ce01.appspot.com/o/CUSCO%2Fgalery%2FgalDos.jpg?alt=media&token=6b8fe5e2-b635-4e28-bb94-8d699836623e",
            "galDos":"https://firebasestorage.googleapis.com/v0/b/mytinerary-6ce01.appspot.com/o/CUSCO%2Fgalery%2FgalUno.jpg?alt=media&token=e9bc6a6a-5c72-4771-a7f8-06781b42025e",
            "galTres":"https://firebasestorage.googleapis.com/v0/b/mytinerary-6ce01.appspot.com/o/CUSCO%2Fgalery%2FgalTres.jpg?alt=media&token=cd560c4c-7e53-4c59-abf4-bd82808f5558"
        },
        { 
            "_id": "", 
            "name": "Sydney", 
            "banner": "https://firebasestorage.googleapis.com/v0/b/mytinerary-6ce01.appspot.com/o/SYDNEY%2Fgalery%2F2c76186a-3daf-4c09-a650-1ad29084a484.jpg?alt=media&token=a8698400-a104-42e7-b02a-9c247a740dcf", 
            "country": "Australia", 
            "language":"English", 
            "image": "https://firebasestorage.googleapis.com/v0/b/mytinerary-6ce01.appspot.com/o/SYDNEY%2Fsidney.jpg?alt=media&token=f3abac69-5921-42c2-a66a-9e871fcdce3b", 
            "info": "Get to know this cosmopolitan city on the shores of Port Jackson, surrounded by national parks with bays and rivers. In Sydney everything mixes, natural resources and human architectural audacity are in harmony", 
            "phrase": "Australia's wonderful star city", 
            "region": "Oceanía", 
            "galUno":"https://firebasestorage.googleapis.com/v0/b/mytinerary-6ce01.appspot.com/o/SYDNEY%2Fgalery%2FgalDos.jpg?alt=media&token=dd7ad0ab-3f7e-4a73-b931-5d954483441f", 
            "galDos":"https://firebasestorage.googleapis.com/v0/b/mytinerary-6ce01.appspot.com/o/SYDNEY%2Fgalery%2FgalUno.jpg?alt=media&token=1ef792ef-c3c6-4d8f-a762-b1653fa3a5be", 
            "galTres":"https://firebasestorage.googleapis.com/v0/b/mytinerary-6ce01.appspot.com/o/SYDNEY%2Fgalery%2FgalTres.jpg?alt=media&token=a27e2dbf-c8cd-49b0-8ac7-1383784aa19e" 
        },
        { 
            "_id": "", 
            "name": "Dubai", 
            "banner": "https://firebasestorage.googleapis.com/v0/b/mytinerary-6ce01.appspot.com/o/DUBAI%2Fgalery%2F0a4e85ab-1b2d-40d4-9b9d-7e7be06eeb3d.jpg?alt=media&token=c59750c1-adf3-4c5d-98d8-52cc2a7d7ba9", 
            "country": "United Arab Emirates", 
            "language":"Arab", 
            "image": "https://firebasestorage.googleapis.com/v0/b/mytinerary-6ce01.appspot.com/o/DUBAI%2Fdubai.jpg?alt=media&token=854fa9a7-c163-431c-97e3-6645e83be40e", 
            "info": "Get to know the city with the most impressive construction projects in the world: luxury hotels and avant-garde architecture to first-class shopping centers, culture and nature", 
            "phrase": "The most luxurious destination in the world", 
            "region": "Asia", 
            "galUno":"https://firebasestorage.googleapis.com/v0/b/mytinerary-6ce01.appspot.com/o/DUBAI%2Fgalery%2FgalDos.jpg?alt=media&token=6bfc9066-6bd1-4d6e-9f31-9017a7ccf53c", 
            "galDos":"https://firebasestorage.googleapis.com/v0/b/mytinerary-6ce01.appspot.com/o/DUBAI%2Fgalery%2FgalUno.jpg?alt=media&token=b09ff8ae-02cd-477f-8d27-9de70368d136", 
            "galTres":"https://firebasestorage.googleapis.com/v0/b/mytinerary-6ce01.appspot.com/o/DUBAI%2Fgalery%2FgalTres.jpg?alt=media&token=40514793-20ef-496f-8954-c4a44a69671a" 
        },
        { 
            "_id": "", 
            "name": "Santiago de Chile", 
            "banner": "https://firebasestorage.googleapis.com/v0/b/mytinerary-6ce01.appspot.com/o/CHILE%2F56185aa5-0c6b-4af3-94dc-0d5127f75fd1.jpg?alt=media&token=e5e2fb6b-d450-40fa-a84e-1d517f3ebdc5", 
            "country": "Chile", 
            "language":"Spanish", 
            "image": "https://firebasestorage.googleapis.com/v0/b/mytinerary-6ce01.appspot.com/o/CHILE%2Fsantiago.jpg?alt=media&token=3d982346-2638-4a37-985b-7da532117cd4", 
            "info": "Get to know one of the smartest cities in the region. Surrounded by mountains that offer attractive panoramas such as visiting the ski centers during the winter, trekking, horseback riding, climbing and discovering the flavors of typical food while enjoying a field day. Also a few hours from beach areas such as Valparaiso", 
            "phrase": "Live Santiago, Gateway of Chile", 
            "region": "Latin America", 
            "galUno":"https://firebasestorage.googleapis.com/v0/b/mytinerary-6ce01.appspot.com/o/CHILE%2FgalTres.jpg?alt=media&token=68b5b046-0e7d-4622-afc9-fd64e516f848", 
            "galDos":"https://firebasestorage.googleapis.com/v0/b/mytinerary-6ce01.appspot.com/o/CHILE%2FgalUno.jpg?alt=media&token=3e4b6f09-b32e-41fd-a31d-c85ff8a3d321", 
            "galTres":"https://firebasestorage.googleapis.com/v0/b/mytinerary-6ce01.appspot.com/o/CHILE%2Fgaldos.jpg?alt=media&token=34243e88-d26b-47f8-9733-93365240949e" 
        },
        { 
            "_id": "", 
            "name": "Antananarivo", 
            "banner": "https://firebasestorage.googleapis.com/v0/b/mytinerary-6ce01.appspot.com/o/MADAGASCAR%2Fgalery%2Fb4da173d-5bed-4f9b-9597-5a77276b50e6.jpg?alt=media&token=ae00d5d4-88bf-4133-8bdd-28f5e3254227", 
            "country": "Republic of Madagascar", 
            "language":"Malgache and French", 
            "image": "https://firebasestorage.googleapis.com/v0/b/mytinerary-6ce01.appspot.com/o/MADAGASCAR%2Fmadagascar.jpg?alt=media&token=62cb4577-840b-4a0e-a679-727311e7a67e", 
            "info": "Visit Antananarivo, a rather bustling city, with very narrow sidewalks and a pronounced provincial charm that makes every traveler who comes here looking for something special fall in love.", 
            "phrase": "In the city of a thousand Soldiers", 
            "region": "Africa", 
            "galUno":"https://firebasestorage.googleapis.com/v0/b/mytinerary-6ce01.appspot.com/o/MADAGASCAR%2Fgalery%2FgalTres.jpg?alt=media&token=831aa4d5-7fef-483d-846e-090920c7cc30", 
            "galDos":"https://firebasestorage.googleapis.com/v0/b/mytinerary-6ce01.appspot.com/o/MADAGASCAR%2Fgalery%2FgalUno.jpg?alt=media&token=2e4da560-b1e3-41ca-86fa-369af66231ee", 
            "galTres":"https://firebasestorage.googleapis.com/v0/b/mytinerary-6ce01.appspot.com/o/MADAGASCAR%2Fgalery%2FgalDos.jpg?alt=media&token=902c61f9-a1b4-4d83-9a33-08273a36eece"
        },
        { 
            "_id": "", 
            "name": "Mónaco", 
            "banner": "https://firebasestorage.googleapis.com/v0/b/mytinerary-6ce01.appspot.com/o/MONACO%2Fce70c2ca-9bfb-4aa6-95aa-15da8a47dae2.jpg?alt=media&token=05c1c2d3-b7e4-4d45-93d3-8e569e9ea31a", 
            "country": "Principado de Mónaco", 
            "language":"Italian, Monegasque, Occitan", 
            "image": "https://firebasestorage.googleapis.com/v0/b/mytinerary-6ce01.appspot.com/o/MONACO%2FMonaco.jpg?alt=media&token=b940079e-82c7-4005-9960-ba17983f8e14", 
            "info": "Visit the second smallest country in the world and know its capital  overlooking the pristine blue waters of the Mediterranean, is a place famed for its glamour and wealth. Monaco attracts lovers of the expensive and curious tourists who visit its main points of interest such as the casino, the port full of yachts or the road where the Formula 1 Grand Prix is ​​held.", 
            "phrase": "Glamorous Destination: Gateway of Monaco", 
            "region": "Europe", 
            "galUno":"https://firebasestorage.googleapis.com/v0/b/mytinerary-6ce01.appspot.com/o/MONACO%2FgalDos.jpg?alt=media&token=5a317f4a-dcac-48af-b99f-2af29a804d8a", 
            "galDos":"https://firebasestorage.googleapis.com/v0/b/mytinerary-6ce01.appspot.com/o/MONACO%2FgalTres.jpg?alt=media&token=f9a38d00-7653-4282-9d38-cbe04f02c95d", 
            "galTres":"https://firebasestorage.googleapis.com/v0/b/mytinerary-6ce01.appspot.com/o/MONACO%2FgalUno.jpeg?alt=media&token=93e4d7c8-ec30-4d03-a504-83512965853b"
        },
        { 
            "_id": "", 
            "name": "Rio de Janeiro", 
            "banner": "https://firebasestorage.googleapis.com/v0/b/mytinerary-6ce01.appspot.com/o/RIO%2Fgalery%2F787a6f5c-de4b-4fe2-a5dc-1456d6a055ea.jpg?alt=media&token=8698e599-6617-4d03-b34e-3f87e9df075f", 
            "country": "Federal Republic of Brazil", 
            "language":"Portuguese", 
            "image": "https://firebasestorage.googleapis.com/v0/b/mytinerary-6ce01.appspot.com/o/RIO%2Frio.jpg?alt=media&token=1dc17a57-c580-4007-b80c-89545299cc0a", 
            "info": "Come to Rio and enjoy its beautiful landscapes surrounded by mountains, sea and beaches that are a dream. Get to know great historical buildings, cultural attractions such as museums, art collections, churches with incredible architecture, and at night you will have dozens of bars and nightclubs to explore.", 
            "phrase": "The jewel of Brazil", 
            "region": "Latin America", 
            "galTres":"https://firebasestorage.googleapis.com/v0/b/mytinerary-6ce01.appspot.com/o/RIO%2Fgalery%2FgalDosu.jpg?alt=media&token=a9d3fa4c-419c-4b72-ae80-3fcd30c47890", 
            "galDos":"https://firebasestorage.googleapis.com/v0/b/mytinerary-6ce01.appspot.com/o/RIO%2Fgalery%2FgalDos.jpg?alt=media&token=00881a35-f4c6-46d9-a2df-25c1e92547ab", 
            "galUno":"https://firebasestorage.googleapis.com/v0/b/mytinerary-6ce01.appspot.com/o/RIO%2Fgalery%2FgalUno.jpg?alt=media&token=93096336-14fd-41f1-9525-e61c5a90d8b4"
        },
        { 
            "_id": "", 
            "name": "Singapore", 
            "banner": "https://firebasestorage.googleapis.com/v0/b/mytinerary-6ce01.appspot.com/o/SINGAPOURE%2Fgalery%2Faa7427d6-ff87-45e4-937d-b2469194d727.jpg?alt=media&token=9d417dba-8632-4a44-8737-6acf8798a9df", 
            "country": "Republic of Singapore", 
            "language":"English, Mandarin, Malay and Tamil", 
            "image": "https://firebasestorage.googleapis.com/v0/b/mytinerary-6ce01.appspot.com/o/SINGAPOURE%2Fsingapur.jpg?alt=media&token=76d6a1c0-59f0-420b-bb27-c7218788ca64", 
            "info": "Get to know one of the main global cities and the nerve center of world trade. This small island will allow you to enjoy quiet parks that border futuristic skyscrapers and luxury shopping malls. Your first trip to Singapore will show you that sometimes the best things come in small packages.", 
            "phrase": "The city of the lion", 
            "region": "Asia", 
            "galUno":"https://firebasestorage.googleapis.com/v0/b/mytinerary-6ce01.appspot.com/o/SINGAPOURE%2Fgalery%2FgalTres.jpg?alt=media&token=4bfa4d12-ff4a-437a-a80d-e264580a19d3", 
            "galDos":"https://firebasestorage.googleapis.com/v0/b/mytinerary-6ce01.appspot.com/o/SINGAPOURE%2Fgalery%2FgalDos.jpg?alt=media&token=79c4e9b8-fd45-4c0e-aed6-1b9f0641c183", 
            "galTres":"https://firebasestorage.googleapis.com/v0/b/mytinerary-6ce01.appspot.com/o/SINGAPOURE%2Fgalery%2FgalUno.jpg?alt=media&token=b83b6fae-967b-4159-8548-b315c077c1d3"
        },
        { 
            "_id": "", 
            "name": "Zurich", 
            "banner": "https://firebasestorage.googleapis.com/v0/b/mytinerary-6ce01.appspot.com/o/ZURICH%2Fgalery%2F47e0aee7-40e1-4ec4-a0b8-de7b2a37faf3.jpg?alt=media&token=121d2a7e-c60a-483e-a54f-146f4ab549cb", 
            "country": "Swiss", 
            "language":"German", 
            "image": "https://firebasestorage.googleapis.com/v0/b/mytinerary-6ce01.appspot.com/o/ZURICH%2Fgalery%2FgalTres.jpg?alt=media&token=6f5dfdaf-4f74-439e-b82a-3a2a4f7c442d", 
            "info": "Come and discover this economic center where various multinational companies have their world headquarters. Known as the most expensive in the world, this luxurious Alpine metropolis overflows with culture, nightlife and art, being one of the main destinations for contemporary art and shopping.", 
            "phrase": "The best city to live", 
            "region": "Europe", 
            "galTres":"https://firebasestorage.googleapis.com/v0/b/mytinerary-6ce01.appspot.com/o/ZURICH%2Fgalery%2Fgal.jpg?alt=media&token=fab37544-ce1d-4e71-853d-f7e47cb76fe8", 
            "galUno":"https://firebasestorage.googleapis.com/v0/b/mytinerary-6ce01.appspot.com/o/ZURICH%2Fgalery%2FgalDos.jpg?alt=media&token=8c57bf01-8126-4dae-8d15-880c1c79bf90", 
            "galDos":"https://firebasestorage.googleapis.com/v0/b/mytinerary-6ce01.appspot.com/o/ZURICH%2Fgalery%2FgaUno.jpg?alt=media&token=b86e30ae-6061-473e-af6c-6ce5f687682f"
        },
        { 
            "_id": "", 
            "name": "Rome", 
            "banner": "https://firebasestorage.googleapis.com/v0/b/mytinerary-6ce01.appspot.com/o/ROME%2Fgalery%2FbannerRome.jpg?alt=media&token=aabb665e-253c-41b7-a39b-241a35c8331b", 
            "country": "Italian Republic", 
            "language":"Italian", 
            "image": "https://firebasestorage.googleapis.com/v0/b/mytinerary-6ce01.appspot.com/o/ROME%2FimageRome.jpg?alt=media&token=d9fa84be-e51e-46ee-b347-b71f9a07d0a6", 
            "info":"Take a trip back in time and come visit the city with the highest concentration of historical and architectural heritage in the world. Get to know first-hand the relics inherited from its different periods of maximum splendor",
            "phrase": "Come To the Città Eterna", 
            "region": "Europe", 
            "galTres":"https://firebasestorage.googleapis.com/v0/b/mytinerary-6ce01.appspot.com/o/ROME%2Fgalery%2Frome.jpg?alt=media&token=f80b5149-51d9-4db3-b188-266acefb844d", 
            "galUno":"https://firebasestorage.googleapis.com/v0/b/mytinerary-6ce01.appspot.com/o/ROME%2Fgalery%2FgalTresRoma.jpg?alt=media&token=d4de45df-f3df-4c24-9bf9-f1878e69b447", 
            "galDos":"https://firebasestorage.googleapis.com/v0/b/mytinerary-6ce01.appspot.com/o/ROME%2Fgalery%2FgalDos.jpg?alt=media&token=5813bad5-244f-4933-b0ff-392bfa4b3bbc"
        }

  
    ]
}